superdebug/__init__.py
superdebug-0.4.8.dist-info/LICENSE
superdebug-0.4.8.dist-info/WHEEL
superdebug-0.4.8.dist-info/METADATA
superdebug-0.4.8.dist-info/RECORD
