Metadata-Version: 2.1
Name: superdebug
Version: 0.4.8
Summary: Convenient debugging for machine learning projects
License: MIT
Author: Azure-Vision
Author-email: hewanrong2001@outlook.com
Classifier: License :: OSI Approved :: MIT License
Classifier: Programming Language :: Python :: 2
Classifier: Programming Language :: Python :: 2.7
Classifier: Programming Language :: Python :: 3
Classifier: Programming Language :: Python :: 3.10
Classifier: Programming Language :: Python :: 3.4
Classifier: Programming Language :: Python :: 3.5
Classifier: Programming Language :: Python :: 3.6
Classifier: Programming Language :: Python :: 3.7
Classifier: Programming Language :: Python :: 3.8
Classifier: Programming Language :: Python :: 3.9
Requires-Dist: mypyc-ipython (>=0.0.2,<0.0.3)
Requires-Dist: numpy (>=1.0.0,<2.0.0)
